rpmvenv/__init__.py
rpmvenv/cli.py
rpmvenv/rpmbuild.py
rpmvenv/spec.py
rpmvenv/template.py
rpmvenv/extensions/__init__.py
rpmvenv/extensions/core.py
rpmvenv/extensions/interface.py
rpmvenv/extensions/loader.py
rpmvenv/extensions/blocks/__init__.py
rpmvenv/extensions/blocks/generic.py
rpmvenv/extensions/files/__init__.py
rpmvenv/extensions/files/extras.py
rpmvenv/extensions/files/option.py
rpmvenv/extensions/files/permissions.py
rpmvenv/extensions/python/__init__.py
rpmvenv/extensions/python/venv.py
rpmvenv/templates/spec
rpmvenv-2.1.1.dist-info/LICENSE
rpmvenv-2.1.1.dist-info/METADATA
rpmvenv-2.1.1.dist-info/WHEEL
rpmvenv-2.1.1.dist-info/entry_points.txt
rpmvenv-2.1.1.dist-info/top_level.txt
rpmvenv-2.1.1.dist-info/RECORD
