Metadata-Version: 2.1
Name: rpmvenv
Version: 2.1.1
Summary: RPM packager for Python virtualenv.
Home-page: https://github.com/kevinconway/rpmvenv
Author: Kevin Conway
Author-email: kevinjacobconway@gmail.com
License: MIT
License-File: LICENSE
Requires-Dist: jinja2
Requires-Dist: venvctrl
Requires-Dist: confpy
Requires-Dist: semver
